{
  "models": {
    "sovova": {
      "id": 1,
      "name": "Sovova",
      "year": "1994",
      "option": "\"A\"",
      "fields": [
        "aa",
        "dsolid",
        "dpa",
        "msolid",
        "ep",
        "dfluid",
        "qq",
        "ttcer",
        "solubility",
        "viscosity",
        "dabf",
        "bb",
        "eb",
        "hc",
        "dc",
        "temperature"
      ],
      "result": {
        "k1": "Solid-phase mass transfer",
        "k2": "Fluid-phase mass transfer",
        "k3": "Critical Concentration"
      }
    },
    "reverchon": {
      "id": 2,
      "name": "Reverchon",
      "year": "1993",
      "option": "\"B\"",
      "fields": [],
      "result": {
        "k1": "Empirical Parameter"
      }
    },
    "esquivel": {
      "id": 3,
      "name": "Esquivel",
      "year": "1999",
      "option": "\"C\"",
      "fields": [],
      "result": {
        "k1": "Empirical Parameter"
      }
    },
    "zekovic": {
      "id": 4,
      "name": "Zekovic",
      "year": "2003",
      "option": "\"D\"",
      "fields": [],
      "result": {
        "k1": "Empirical Parameter",
        "k2": "Empirical Parameter"
      }
    },
    "nguyen": {
      "id": 5,
      "name": "Nguyen",
      "year": "1991",
      "option": "\"E\"",
      "fields": [],
      "result": {
        "k1": "Empirical Parameter"
      }
    },
    "verljkovic": {
      "id": 6,
      "name": "Veljkovic and Milenovic",
      "year": "2002",
      "option": "\"F\"",
      "fields": [],
      "result": {
        "k1": "Solid-phase mass transfer coefficient",
        "k2": "Fluid-phase mass transfer coefficient",
        "k3": "Critical Concentration coefficient"
      }
    },
    "pkm": {
      "id": 7,
      "name": "PKM",
      "year": "2012",
      "option": "\"G\"",
      "fields": [],
      "result": {
        "k1": "Empirical Parameter",
        "k2": "Empirical Parameter"
      }
    }
  }
}
